{
  "stockCode": "PDD",
  "metric": "TTM Net EPS",
  "source": "Macrotrends",
  "sourceUrl": "https://www.macrotrends.net/stocks/charts/PDD/pdd-holdings/pe-ratio",
  "range": {
    "start": "2019-06-30",
    "end": "2026-03-31"
  },
  "epsByDate": {
    "2019-06-30": -0.22,
    "2019-09-30": -0.34,
    "2019-12-31": -0.88,
    "2020-03-31": -1.14,
    "2020-06-30": -1.13,
    "2020-09-30": -0.95,
    "2020-12-31": -0.92,
    "2021-03-31": -0.78,
    "2021-06-30": -0.4,
    "2021-09-30": -0.12,
    "2021-12-31": 0.84,
    "2022-03-31": 1.49,
    "2022-06-30": 2.15,
    "2022-09-30": 3,
    "2022-12-31": 3.16,
    "2023-03-31": 3.68,
    "2023-06-30": 3.99,
    "2023-09-30": 4.41,
    "2023-12-31": 5.8,
    "2024-03-31": 7.62,
    "2024-06-30": 9.35,
    "2024-09-30": 10.31,
    "2024-12-31": 10.4,
    "2025-03-31": 9.14,
    "2025-06-30": 9.07,
    "2025-09-30": 9.43,
    "2025-12-31": 9.44,
    "2026-03-31": 9.3
  }
}
